RTL/two flop synchroniser.v
module d_flop(q, clk, d, rst);

    input clk, d, rst;
    output reg q;

    always @(posedge clk)
    begin
        if(rst)
        begin
            q <= 0;
        end
        else begin
            q <= d;
        end
    end

endmodule

module two_flop_synchronizer(q, clk, d, rst);

    input clk, d, rst;
    output q;
    wire t;

    d_flop D0(.q(t), .clk(clk), .d(d), .rst(rst));
    d_flop D1(.q(q), .clk(clk), .d(t), .rst(rst));

endmodule

RTL/dual_ram.v
module dual_rom(data_in, data_out, w_clk, r_clk, w_en, r_en,
w_ptr, r_ptr, full, empty);

    input [7:0] data_in;
    input w_clk, r_clk, w_en, r_en, full, empty;
    input [4:0] w_ptr, r_ptr;
    output reg [7:0] data_out;

    reg [7:0] mem [15:0];

    always @(posedge w_clk or posedge r_clk)
    begin
        if(w_en && !full)
        begin
            mem[w_ptr[3:0]] <= data_in;
        end
        if(r_en && !empty)
        begin
            data_out <= mem[r_ptr[3:0]];
        end
    end

endmodule

RTL/binary to grey.v
module binary_to_grey(out, in);

    input [4:0] in;
    output [4:0] out;

    assign out[4] = in[4];
    assign out[3] = in[4] ^ in[3];
    assign out[2] = in[3] ^ in[2];
    assign out[1] = in[2] ^ in[1];
    assign out[0] = in[1] ^ in[0];

endmodule

RTL/grey to binary.v
module grey_to_binary(out, in);

    input [4:0] in;
    output [4:0] out;

    assign out[4] = in[4];
    assign out[3] = out[4] ^ in[3];
    assign out[2] = out[3] ^ in[2];
    assign out[1] = out[2] ^ in[1];
    assign out[0] = out[1] ^ in[0];

endmodule

RTL/write pointef handler.v
module write_pointer_handler(full, b_wptr, g_wptr,
wclk, wrst_n, g_rptr_sync, wr_en);

    input wclk, wrst_n, wr_en;
    input [4:0] g_rptr_sync;
    output full;
    output reg [4:0] b_wptr;
    output [4:0] g_wptr;

    wire [4:0] b_rptr_sync;

    grey_to_binary G2(b_rptr_sync, g_rptr_sync);
    binary_to_grey B2(g_wptr, b_wptr);

    assign full = ({~b_wptr[4],b_wptr[3:0]} == b_rptr_sync);

    always @(posedge wclk)
    begin
        if(!wrst_n)
        begin
            b_wptr <= 0;
        end
        else begin
            if(wr_en && !full) begin
                b_wptr <= b_wptr + 1;
            end
        end
    end

endmodule

RTL/read pointer handler.v
module read_pointer_handler(empty, g_rptr, b_rptr, g_wptr_sync,
r_clk, r_en, rrst_n);

    input r_clk, r_en, rrst_n;
    input [4:0] g_wptr_sync;
    output reg [4:0] b_rptr;
    output [4:0] g_rptr;
    output empty;

    wire [4:0] b_wptr_sync;

    grey_to_binary G1(b_wptr_sync, g_wptr_sync);
    binary_to_grey B1(g_rptr, b_rptr);

    assign empty = (b_rptr == b_wptr_sync);

    always @(r_clk)
    begin
        if(rrst_n)
        begin
            b_rptr <= 0;
        end
        else begin
            if(r_en && !empty)
            begin
                b_rptr <= b_rptr + 1;
            end
        end
    end

endmodule

RTL/Async_fifo.v

module Async_fifo(data_out, full, empty, w_clk, r_clk, w_en,
r_en, w_rst_n, rrst_n, data_in);

    input [7:0] data_in;
    input w_clk, r_clk, w_en, r_en, w_rst_n, rrst_n;
    output full, empty;
    output [7:0] data_out;

    wire [4:0] b_rptr, b_wptr, g_rptr, g_wptr, g_wptr_sync, g_rptr_sync;

    read_pointer_handler R(.empty(empty), .g_rptr(g_rptr), .b_rptr(b_rptr), 
.g_wptr_sync(g_wptr_sync),.r_clk(r_clk), .r_en(r_en), .rrst_n(rrst_n));

    write_pointer_handler W(.full(full), .b_wptr(b_wptr), .g_wptr(g_wptr),
.wclk(w_clk), .wrst_n(w_rst_n), .g_rptr_sync(g_rptr_sync), .wr_en(w_en));

    dual_rom D(.data_in(data_in), .data_out(data_out), .w_clk(w_clk), .r_clk(r_clk),
.w_en(w_en), .r_en(r_en), .w_ptr(b_wptr), .r_ptr(b_rptr), .full(full), .empty(empty));

    two_flop_synchronizer T1(.q(g_wptr_sync[4]), .clk(r_clk), .d(g_wptr[4]), .rst(rrst_n));
    two_flop_synchronizer T2(.q(g_wptr_sync[3]), .clk(r_clk), .d(g_wptr[3]), .rst(rrst_n));
    two_flop_synchronizer T3(.q(g_wptr_sync[2]), .clk(r_clk), .d(g_wptr[2]), .rst(rrst_n));
    two_flop_synchronizer T4(.q(g_wptr_sync[1]), .clk(r_clk), .d(g_wptr[1]), .rst(rrst_n));
    two_flop_synchronizer T5(.q(g_wptr_sync[0]), .clk(r_clk), .d(g_wptr[0]), .rst(rrst_n));
    two_flop_synchronizer T6(.q(g_rptr_sync[4]), .clk(w_clk), .d(g_rptr[4]), .rst(w_rst_n));
    two_flop_synchronizer T7(.q(g_rptr_sync[3]), .clk(w_clk), .d(g_rptr[3]), .rst(w_rst_n));
    two_flop_synchronizer T8(.q(g_rptr_sync[2]), .clk(w_clk), .d(g_rptr[2]), .rst(w_rst_n));
    two_flop_synchronizer T9(.q(g_rptr_sync[1]), .clk(w_clk), .d(g_rptr[1]), .rst(w_rst_n));
    two_flop_synchronizer T10(.q(g_rptr_sync[0]), .clk(w_clk), .d(g_rptr[0]), .rst(w_rst_n));

endmodule

test/async_fifo_tb.v
`timescale 1ns/1ps

module tb_async_fifo;


    reg                  wr_clk = 0;
    reg                  rd_clk = 0;
    reg                  wr_rst_n = 0;
    reg                  rd_rst_n = 0;
    reg                  wr_en = 0;
    reg  [7:0]     wr_data = 0;
    wire                 full;
    reg                  rd_en = 0;
    wire [7:0]     rd_data;
    wire                 empty;

    integer wr_count   = 0;
    integer rd_count   = 0;
    integer errors     = 0;
    integer next_wdata  = 0;

    reg [7:0] expected_q [0:2047];
    integer wr_ptr_sb = 0;
    integer rd_ptr_sb = 0;

    Async_fifo D (.data_out(rd_data), .full(full), .empty(empty), .w_clk(wr_clk), 
.r_clk(rd_clk), .w_en(wr_en), .r_en(rd_en), .w_rst_n(wr_rst_n), .rrst_n(rd_rst_n),
.data_in(wr_data));

    always #5  wr_clk = ~wr_clk;   // 100.0 MHz
    always #7  rd_clk = ~rd_clk;   //  71.4 MHz

    initial begin
        wr_rst_n = 0; rd_rst_n = 0;
        repeat (5) @(posedge wr_clk);
        wr_rst_n = 1;
        repeat (5) @(posedge rd_clk);
        rd_rst_n = 1;
    end

    integer wcycles = 0;
    always @(posedge wr_clk) begin
        if (!wr_rst_n) begin
            wr_en <= 0;
        end else begin
            // 1) Record the effect of whatever wr_en/wr_data were driving
            //    THIS edge (i.e. exactly what the DUT just latched).
            if (wr_en && !full) begin
                expected_q[wr_ptr_sb] = wr_data;
                wr_ptr_sb = wr_ptr_sb + 1;
                wr_count  = wr_count + 1;
            end
            // 2) Decide stimulus to drive for the NEXT edge.
            wcycles = wcycles + 1;
            if (wcycles <= 600 && !full && ($random % 3 != 0)) begin
                wr_en   <= 1;
                wr_data <= next_wdata[7:0];
                next_wdata = next_wdata + 1;
            end else begin
                wr_en <= 0;
            end
        end
    end

    integer rcycles = 0;
    // always @(posedge rd_clk) begin
    //     if (!rd_rst_n) begin
    //         rd_en <= 0;
    //     end else begin
    //         // 1) Record the effect of whatever rd_en was driving THIS edge.
    //         if (rd_en && !empty) begin
    //             if (rd_data !== expected_q[rd_ptr_sb]) begin
    //                 $display("MISMATCH at t=%0t: got %0d expected %0d (rd_ptr_sb=%0d)",
    //                           $time, rd_data, expected_q[rd_ptr_sb], rd_ptr_sb);
    //                 errors = errors + 1;
    //             end
    //             rd_ptr_sb = rd_ptr_sb + 1;
    //             rd_count  = rd_count + 1;
    //         end
    //         // 2) Decide stimulus for the NEXT edge.
    //         rcycles = rcycles + 1;
    //         if (!empty && ($random % 3 != 0))
    //             rd_en <= 1;
    //         else
    //             rd_en <= 0;

    //         if (rcycles > 1200 && rd_count >= wr_count && !(wr_en || (wcycles<=600))) begin
    //             // drained everything after the write process stopped
    //         end
    //     end
    // end

    always @(posedge rd_clk) begin
    if (!rd_rst_n) begin
        rd_en <= 0;
    end
    else begin

        if (rd_en && !empty) begin
            #1;

            if (rd_data !== expected_q[rd_ptr_sb]) begin
                $display("MISMATCH at t=%0t: got %0d expected %0d (rd_ptr_sb=%0d)",
                          $time, rd_data, expected_q[rd_ptr_sb], rd_ptr_sb);
                errors = errors + 1;
            end

            rd_ptr_sb = rd_ptr_sb + 1;
            rd_count  = rd_count + 1;
        end

        rcycles = rcycles + 1;

        if (!empty && ($random % 3 != 0))
            rd_en <= 1;
        else
            rd_en <= 0;
    end
end

    initial begin

        $dumpfile("async_fifo.vcd");
        $dumpvars(0, tb_async_fifo);
        wait (wr_rst_n && rd_rst_n);
        wait (wcycles > 600);          // write stimulus phase complete
        // Keep clocking reads until fully drained
        wait (rd_count == wr_count);
        #100;
        $display("--------------------------------------------------");
        $display("Total written = %0d, Total read = %0d", wr_count, rd_count);
        if (errors == 0 && wr_count == rd_count)
            $display("TEST PASSED: all %0d words verified, no data corruption", rd_count);
        else
            $display("TEST FAILED: %0d mismatches, wr_count=%0d rd_count=%0d",
                      errors, wr_count, rd_count);
        $display("--------------------------------------------------");
        $finish;
    end

    initial begin
        #200000;
        $display("TIMEOUT - simulation did not finish in time");
        $finish;
    end

endmodule

test/sim_results/dump.vcd
$date
	Mon Aug 24 00:59:51 2026
$end
$version
	Icarus Verilog
$end
$timescale
	1ps
$end
$scope module tb_async_fifo $end
$var wire 8 ! rd_data [7:0] $end
$var wire 1 " full $end
$var wire 1 # empty $end
$var reg 1 $ rd_clk $end
$var reg 1 % rd_en $end
$var reg 1 & rd_rst_n $end
$var reg 1 ' wr_clk $end
$var reg 8 ( wr_data [7:0] $end
$var reg 1 ) wr_en $end
$var reg 1 * wr_rst_n $end
$var integer 32 + errors [31:0] $end
$var integer 32 , next_wdata [31:0] $end
$var integer 32 - rcycles [31:0] $end
$var integer 32 . rd_count [31:0] $end
$var integer 32 / rd_ptr_sb [31:0] $end
$var integer 32 0 wcycles [31:0] $end
$var integer 32 1 wr_count [31:0] $end
$var integer 32 2 wr_ptr_sb [31:0] $end
$scope module D $end
$var wire 8 3 data_in [7:0] $end
$var wire 1 $ r_clk $end
$var wire 1 % r_en $end
$var wire 1 & rrst_n $end
$var wire 1 ' w_clk $end
$var wire 1 ) w_en $end
$var wire 1 * w_rst_n $end
$var wire 5 4 g_wptr_sync [4:0] $end
$var wire 5 5 g_wptr [4:0] $end
$var wire 5 6 g_rptr_sync [4:0] $end
$var wire 5 7 g_rptr [4:0] $end
$var wire 1 " full $end
$var wire 1 # empty $end
$var wire 8 8 data_out [7:0] $end
$var wire 5 9 b_wptr [4:0] $end
$var wire 5 : b_rptr [4:0] $end
$scope module D $end
$var wire 8 ; data_in [7:0] $end
$var wire 1 $ r_clk $end
$var wire 1 % r_en $end
$var wire 1 ' w_clk $end
$var wire 1 ) w_en $end
$var wire 5 < w_ptr [4:0] $end
$var wire 5 = r_ptr [4:0] $end
$var wire 1 " full $end
$var wire 1 # empty $end
$var reg 8 > data_out [7:0] $end
$upscope $end
$scope module R $end
$var wire 5 ? g_wptr_sync [4:0] $end
$var wire 1 $ r_clk $end
$var wire 1 % r_en $end
$var wire 1 & rrst_n $end
$var wire 5 @ g_rptr [4:0] $end
$var wire 1 # empty $end
$var wire 5 A b_wptr_sync [4:0] $end
$var reg 5 B b_rptr [4:0] $end
$scope module B1 $end
$var wire 5 C in [4:0] $end
$var wire 5 D out [4:0] $end
$upscope $end
$scope module G1 $end
$var wire 5 E in [4:0] $end
$var wire 5 F out [4:0] $end
$upscope $end
$upscope $end
$scope module T1 $end
$var wire 1 $ clk $end
$var wire 1 G d $end
$var wire 1 & rst $end
$var wire 1 H t $end
$var wire 1 I q $end
$scope module D0 $end
$var wire 1 $ clk $end
$var wire 1 G d $end
$var wire 1 & rst $end
$var reg 1 H q $end
$upscope $end
$scope module D1 $end
$var wire 1 $ clk $end
$var wire 1 H d $end
$var wire 1 & rst $end
$var reg 1 I q $end
$upscope $end
$upscope $end
$scope module T10 $end
$var wire 1 ' clk $end
$var wire 1 J d $end
$var wire 1 * rst $end
$var wire 1 K t $end
$var wire 1 L q $end
$scope module D0 $end
$var wire 1 ' clk $end
$var wire 1 J d $end
$var wire 1 * rst $end
$var reg 1 K q $end
$upscope $end
$scope module D1 $end
$var wire 1 ' clk $end
$var wire 1 K d $end
$var wire 1 * rst $end
$var reg 1 L q $end
$upscope $end
$upscope $end
$scope module T2 $end
$var wire 1 $ clk $end
$var wire 1 M d $end
$var wire 1 & rst $end
$var wire 1 N t $end
$var wire 1 O q $end
$scope module D0 $end
$var wire 1 $ clk $end
$var wire 1 M d $end
$var wire 1 & rst $end
$var reg 1 N q $end
$upscope $end
$scope module D1 $end
$var wire 1 $ clk $end
$var wire 1 N d $end
$var wire 1 & rst $end
$var reg 1 O q $end
$upscope $end
$upscope $end
$scope module T3 $end
$var wire 1 $ clk $end
$var wire 1 P d $end
$var wire 1 & rst $end
$var wire 1 Q t $end
$var wire 1 R q $end
$scope module D0 $end
$var wire 1 $ clk $end
$var wire 1 P d $end
$var wire 1 & rst $end
$var reg 1 Q q $end
$upscope $end
$scope module D1 $end
$var wire 1 $ clk $end
$var wire 1 Q d $end
$var wire 1 & rst $end
$var reg 1 R q $end
$upscope $end
$upscope $end
$scope module T4 $end
$var wire 1 $ clk $end
$var wire 1 S d $end
$var wire 1 & rst $end
$var wire 1 T t $end
$var wire 1 U q $end
$scope module D0 $end
$var wire 1 $ clk $end
$var wire 1 S d $end
$var wire 1 & rst $end
$var reg 1 T q $end
$upscope $end
$scope module D1 $end
$var wire 1 $ clk $end
$var wire 1 T d $end
$var wire 1 & rst $end
$var reg 1 U q $end
$upscope $end
$upscope $end
$scope module T5 $end
$var wire 1 $ clk $end
$var wire 1 V d $end
$var wire 1 & rst $end
$var wire 1 W t $end
$var wire 1 X q $end
$scope module D0 $end
$var wire 1 $ clk $end
$var wire 1 V d $end
$var wire 1 & rst $end
$var reg 1 W q $end
$upscope $end
$scope module D1 $end
$var wire 1 $ clk $end
$var wire 1 W d $end
$var wire 1 & rst $end
$var reg 1 X q $end
$upscope $end
$upscope $end
$scope module T6 $end
$var wire 1 ' clk $end
$var wire 1 Y d $end
$var wire 1 * rst $end
$var wire 1 Z t $end
$var wire 1 [ q $end
$scope module D0 $end
$var wire 1 ' clk $end
$var wire 1 Y d $end
$var wire 1 * rst $end
$var reg 1 Z q $end
$upscope $end
$scope module D1 $end
$var wire 1 ' clk $end
$var wire 1 Z d $end
$var wire 1 * rst $end
$var reg 1 [ q $end
$upscope $end
$upscope $end
$scope module T7 $end
$var wire 1 ' clk $end
$var wire 1 \ d $end
$var wire 1 * rst $end
$var wire 1 ] t $end
$var wire 1 ^ q $end
$scope module D0 $end
$var wire 1 ' clk $end
$var wire 1 \ d $end
$var wire 1 * rst $end
$var reg 1 ] q $end
$upscope $end
$scope module D1 $end
$var wire 1 ' clk $end
$var wire 1 ] d $end
$var wire 1 * rst $end
$var reg 1 ^ q $end
$upscope $end
$upscope $end
$scope module T8 $end
$var wire 1 ' clk $end
$var wire 1 _ d $end
$var wire 1 * rst $end
$var wire 1 ` t $end
$var wire 1 a q $end
$scope module D0 $end
$var wire 1 ' clk $end
$var wire 1 _ d $end
$var wire 1 * rst $end
$var reg 1 ` q $end
$upscope $end
$scope module D1 $end
$var wire 1 ' clk $end
$var wire 1 ` d $end
$var wire 1 * rst $end
$var reg 1 a q $end
$upscope $end
$upscope $end
$scope module T9 $end
$var wire 1 ' clk $end
$var wire 1 b d $end
$var wire 1 * rst $end
$var wire 1 c t $end
$var wire 1 d q $end
$scope module D0 $end
$var wire 1 ' clk $end
$var wire 1 b d $end
$var wire 1 * rst $end
$var reg 1 c q $end
$upscope $end
$scope module D1 $end
$var wire 1 ' clk $end
$var wire 1 c d $end
$var wire 1 * rst $end
$var reg 1 d q $end
$upscope $end
$upscope $end
$scope module W $end
$var wire 5 e g_rptr_sync [4:0] $end
$var wire 1 ' wclk $end
$var wire 1 ) wr_en $end
$var wire 1 * wrst_n $end
$var wire 5 f g_wptr [4:0] $end
$var wire 1 " full $end
$var wire 5 g b_rptr_sync [4:0] $end
$var reg 5 h b_wptr [4:0] $end
$scope module B2 $end
$var wire 5 i in [4:0] $end
$var wire 5 j out [4:0] $end
$upscope $end
$scope module G2 $end
$var wire 5 k in [4:0] $end
$var wire 5 l out [4:0] $end
$upscope $end
$upscope $end
$upscope $end
$upscope $end
$enddefinitions $end
$comment Show the parameter values. $end
$dumpall
$end
#0
$dumpvars
b0 l
b0 k
b0 j
b0 i
b0 h
b0 g
b0 f
b0 e
0d
0c
0b
0a
0`
0_
0^
0]
0\
0[
0Z
0Y
0X
0W
0V
0U
0T
0S
0R
0Q
0P
0O
0N
0M
0L
0K
0J
0I
0H
0G
b0 F
b0 E
b0 D
b0 C
b0 B
b0 A
b0 @
b0 ?
bx >
b0 =
b0 <
b0 ;
b0 :
b0 9
bx 8
b0 7
b0 6
b0 5
b0 4
b0 3
b0 2
b0 1
b0 0
b0 /
b0 .
b0 -
b0 ,
b0 +
0*
0)
b0 (
0'
0&
0%
0$
1#
0"
bx !
$end
#5000
1'
#7000
1$
#10000
0'
#14000
0$
#15000
1'
#20000
0'
#21000
1$
#25000
1'
#28000
0$
#30000
0'
#35000
1'
1$
#40000
0'
#42000
0$
#45000
1*
1'
#49000
1$
#50000
0'
#55000
1)
b1 ,
b1 0
1'
#56000
0$
#60000
0'
#63000
1$
#65000
1V
b1 5
b1 f
b1 j
b1 (
b1 3
b1 ;
b1 9
b1 <
b1 h
b1 i
b10 ,
b10 0
b1 1
b1 2
1'
#70000
0'
0$
#75000
1S
b11 5
b11 f
b11 j
0)
b10 9
b10 <
b10 h
b10 i
b11 0
b10 1
b10 2
1'
#77000
1$
#80000
0'
#84000
0$
#85000
b10 (
b10 3
b10 ;
1)
b11 ,
b100 0
1'
#90000
0'
#91000
1$
#95000
0V
b10 5
b10 f
b10 j
0)
b11 9
b11 <
b11 h
b11 i
b101 0
b11 1
b11 2
1'
#98000
0$
#100000
0'
#105000
b11 (
b11 3
b11 ;
1)
b100 ,
b110 0
b1 -
1&
1'
1$
#110000
0'
#112000
0$
#115000
1P
b110 5
b110 f
b110 j
b100 (
b100 3
b100 ;
b100 9
b100 <
b100 h
b100 i
b101 ,
b111 0
b100 1
b100 2
1'
#119000
1T
1Q
b10 -
1$
#120000
0'
#125000
1V
b111 5
b111 f
b111 j
0)
b101 9
b101 <
b101 h
b101 i
b1000 0
b101 1
b101 2
1'
#126000
0$
#130000
0'
#133000
0#
b100 A
b100 F
1R
b110 4
b110 ?
b110 E
1U
1W
b11 -
1$
#135000
b1001 0
1'
#140000
0'
0$
#145000
b101 (
b101 3
b101 ;
1)
b110 ,
b1010 0
1'
#147000
b101 A
b101 F
b111 4
b111 ?
b111 E
1X
b100 -
1$
#150000
0'
#154000
0$
#155000
0S
b101 5
b101 f
b101 j
b110 (
b110 3
b110 ;
b110 9
b110 <
b110 h
b110 i
b111 ,
b1011 0
b110 1
b110 2
1'
#160000
0'
#161000
0T
b101 -
1$
#165000
0V
b100 5
b100 f
b100 j
b111 (
b111 3
b111 ;
b111 9
b111 <
b111 h
b111 i
b1000 ,
b1100 0
b111 1
b111 2
1'
#168000
0$
#170000
0'
#175000
1M
b1100 5
b1100 f
b1100 j
b110 A
b110 F
b1000 (
b1000 3
b1000 ;
b1000 9
b1000 <
b1000 h
b1000 i
1%
0W
b101 4
b101 ?
b101 E
0U
b1001 ,
b1101 0
b1000 1
b1000 2
b110 -
1'
1$
#180000
0'
#182000
0$
#185000
1V
b1101 5
b1101 f
b1101 j
0)
b1001 9
b1001 <
b1001 h
b1001 i
b1110 0
b1001 1
b1001 2
1'
#189000
1J
b1 7
b1 @
b1 D
b111 A
b111 F
b0 !
b0 8
b0 >
b1 :
b1 =
b1 B
b1 C
1N
1W
b100 4
b100 ?
b100 E
0X
1$
#190000
b111 -
b1 .
b1 /
0'
#195000
1K
b1111 0
1'
#196000
0$
#200000
0'
#203000
1b
b1001 A
b1001 F
b11 7
b11 @
b11 D
b1 !
b1 8
b1 >
1X
b1101 4
b1101 ?
b1101 E
1O
b10 :
b10 =
b10 B
b10 C
1$
#204000
b1000 -
b10 .
b10 /
#205000
b1 g
b1 l
b1001 (
b1001 3
b1001 ;
1)
b1 6
b1 e
b1 k
1L
1c
b1010 ,
b10000 0
1'
#210000
0'
0$
#215000
1S
b1111 5
b1111 f
b1111 j
b10 g
b10 l
0)
b1010 9
b1010 <
b1010 h
b1010 i
b11 6
b11 e
b11 k
1d
b10001 0
b1010 1
b1010 2
1'
#217000
0J
b10 7
b10 @
b10 D
b10 !
b10 8
b10 >
b11 :
b11 =
b11 B
b11 C
1T
1$
#218000
0%
b1001 -
b11 .
b11 /
#220000
0'
#224000
0$
#225000
b1010 (
b1010 3
b1010 ;
1)
0K
b1011 ,
b10010 0
1'
#230000
0'
#231000
b1010 A
b1010 F
b1111 4
b1111 ?
b1111 E
1U
b1010 -
1$
#235000
0V
b1110 5
b1110 f
b1110 j
b11 g
b11 l
0)
b1011 9
b1011 <
b1011 h
b1011 i
b10 6
b10 e
b10 k
0L
b10011 0
b1011 1
b1011 2
1'
#238000
0$
#240000
0'
#245000
b1011 (
b1011 3
b1011 ;
1)
1%
0W
b1100 ,
b10100 0
b1011 -
1'
1$
#250000
0'
#252000
0$
#255000
0P
b1010 5
b1010 f
b1010 j
0)
b1100 9
b1100 <
b1100 h
b1100 i
b10101 0
b1100 1
b1100 2
1'
#259000
1_
b1011 A
b1011 F
b110 7
b110 @
b110 D
b11 !
b11 8
b11 >
b1110 4
b1110 ?
b1110 E
0X
0Q
b100 :
b100 =
b100 B
b100 C
1$
#260000
0%
b1100 -
b100 .
b100 /
0'
#265000
1`
b10110 0
1'
#266000
0$
#270000
0'
#273000
b1100 A
b1100 F
1%
b1010 4
b1010 ?
b1010 E
0R
b1101 -
1$
#275000
b100 g
b100 l
b1100 (
b1100 3
b1100 ;
1)
b110 6
b110 e
b110 k
1a
b1101 ,
b10111 0
1'
#280000
0'
0$
#285000
1V
b1011 5
b1011 f
b1011 j
b1101 (
b1101 3
b1101 ;
b1101 9
b1101 <
b1101 h
b1101 i
b1110 ,
b11000 0
b1101 1
b1101 2
1'
#287000
1J
b111 7
b111 @
b111 D
b100 !
b100 8
b100 >
1W
b101 :
b101 =
b101 B
b101 C
1$
#288000
0%
b1110 -
b101 .
b101 /
#290000
0'
#294000
0$
#295000
0S
b1001 5
b1001 f
b1001 j
b1110 (
b1110 3
b1110 ;
b1110 9
b1110 <
b1110 h
b1110 i
1K
b1111 ,
b11001 0
b1110 1
b1110 2
1'
#300000
0'
#301000
b1101 A
b1101 F
1%
0T
b1011 4
b1011 ?
b1011 E
1X
b1111 -
1$
#305000
0V
b101 g
b101 l
b1000 5
b1000 f
b1000 j
b1111 (
b1111 3
b1111 ;
b111 6
b111 e
b111 k
1L
b1111 9
b1111 <
b1111 h
b1111 i
b10000 ,
b11010 0
b1111 1
b1111 2
1'
#308000
0$
#310000
0'
#315000
0b
1G
b1110 A
b1110 F
b101 7
b101 @
b101 D
b11000 5
b11000 f
b11000 j
0)
b10000 9
b10000 <
b10000 h
b10000 i
b101 !
b101 8
b101 >
0W
b1001 4
b1001 ?
b1001 E
0U
b110 :
b110 =
b110 B
b110 C
b11011 0
b10000 1
b10000 2
1'
1$
#316000
b10000 -
b110 .
b110 /
#320000
0'
#322000
0$
#325000
0c
b11100 0
1'
#329000
0J
b100 7
b100 @
b100 D
b1111 A
b1111 F
b110 !
b110 8
b110 >
b111 :
b111 =
b111 B
b111 C
1H
b1000 4
b1000 ?
b1000 E
0X
1$
#330000
0%
b10001 -
b111 .
b111 /
0'
#335000
b110 g
b110 l
b10000 (
b10000 3
b10000 ;
1)
b101 6
b101 e
b101 k
0d
0K
b10001 ,
b11101 0
1'
#336000
0$
#340000
0'
#343000
b10000 A
b10000 F
1%
b11000 4
b11000 ?
b11000 E
1I
b10010 -
1$
#345000
1V
b111 g
b111 l
b11001 5
b11001 f
b11001 j
0)
b100 6
b100 e
b100 k
0L
b10001 9
b10001 <
b10001 h
b10001 i
b11110 0
b10001 1
b10001 2
1'
#350000
0'
0$
#355000
b10001 (
b10001 3
b10001 ;
1)
b10010 ,
b11111 0
1'
#357000
1\
b1100 7
b1100 @
b1100 D
b111 !
b111 8
b111 >
b1000 :
b1000 =
b1000 B
b1000 C
1W
1$
#358000
b10011 -
b1000 .
b1000 /
#360000
0'
#364000
0$
#365000
1S
b11011 5
b11011 f
b11011 j
b10010 (
b10010 3
b10010 ;
1]
b10010 9
b10010 <
b10010 h
b10010 i
b10011 ,
b100000 0
b10010 1
b10010 2
1'
#370000
0'
#371000
1J
b10001 A
b10001 F
b1101 7
b1101 @
b1101 D
b1000 !
b1000 8
b1000 >
b11001 4
b11001 ?
b11001 E
1X
1T
b1001 :
b1001 =
b1001 B
b1001 C
1$
#372000
0%
b10100 -
b1001 .
b1001 /
#375000
0V
b11010 5
b11010 f
b11010 j
b1000 g
b1000 l
0)
b10011 9
b10011 <
b10011 h
b10011 i
b1100 6
b1100 e
b1100 k
1^
1K
b100001 0
b10011 1
b10011 2
1'
#378000
0$
#380000
0'
#385000
b1001 g
b1001 l
b10010 A
b10010 F
b10011 (
b10011 3
b10011 ;
1)
b1101 6
b1101 e
b1101 k
1L
1%
b11011 4
b11011 ?
b11011 E
1U
0W
b10100 ,
b100010 0
b10101 -
1'
1$
#390000
0'
#392000
0$
#395000
1P
b11110 5
b11110 f
b11110 j
b10100 (
b10100 3
b10100 ;
b10100 9
b10100 <
b10100 h
b10100 i
b10101 ,
b100011 0
b10100 1
b10100 2
1'
#399000
1b
b10011 A
b10011 F
b1111 7
b1111 @
b1111 D
b1001 !
b1001 8
b1001 >
b11010 4
b11010 ?
b11010 E
0X
1Q
b1010 :
b1010 =
b1010 B
b1010 C
1$
#400000
b10110 -
b1010 .
b1010 /
0'
#405000
1V
b11111 5
b11111 f
b11111 j
b10101 (
b10101 3
b10101 ;
1c
b10101 9
b10101 <
b10101 h
b10101 i
b10110 ,
b100100 0
b10101 1
b10101 2
1'
#406000
0$
#410000
0'
#413000
0J
b1110 7
b1110 @
b1110 D
b10100 A
b10100 F
b1010 !
b1010 8
b1010 >
b1011 :
b1011 =
b1011 B
b1011 C
b11110 4
b11110 ?
b11110 E
1R
1W
1$
#414000
b10111 -
b1011 .
b1011 /
#415000
0S
b11101 5
b11101 f
b11101 j
b1010 g
b1010 l
b10110 (
b10110 3
b10110 ;
b10110 9
b10110 <
b10110 h
b10110 i
b1111 6
b1111 e
b1111 k
1d
0K
b10111 ,
b100101 0
b10110 1
b10110 2
1'
#420000
0'
0$
#425000
0V
b1011 g
b1011 l
b11100 5
b11100 f
b11100 j
b10111 (
b10111 3
b10111 ;
b1110 6
b1110 e
b1110 k
0L
b10111 9
b10111 <
b10111 h
b10111 i
b11000 ,
b100110 0
b10111 1
b10111 2
1'
#427000
0_
b10101 A
b10101 F
b1010 7
b1010 @
b1010 D
b1011 !
b1011 8
b1011 >
b11111 4
b11111 ?
b11111 E
1X
0W
0T
b1100 :
b1100 =
b1100 B
b1100 C
1$
#428000
0%
b11000 -
b1100 .
b1100 /
#430000
0'
#434000
0$
#435000
0M
b10100 5
b10100 f
b10100 j
b11000 (
b11000 3
b11000 ;
b11000 9
b11000 <
b11000 h
b11000 i
0`
b11001 ,
b100111 0
b11000 1
b11000 2
1'
#440000
0'
#441000
b10111 A
b10111 F
0N
0U
b11100 4
b11100 ?
b11100 E
0X
b11001 -
1$
#445000
1V
b1100 g
b1100 l
b10101 5
b10101 f
b10101 j
b11001 (
b11001 3
b11001 ;
b1010 6
b1010 e
b1010 k
0a
b11001 9
b11001 <
b11001 h
b11001 i
b11010 ,
b101000 0
b11001 1
b11001 2
1'
#448000
0$
#450000
0'
#455000
1S
b10111 5
b10111 f
b10111 j
b11000 A
b11000 F
b11010 (
b11010 3
b11010 ;
b11010 9
b11010 <
b11010 h
b11010 i
1%
1W
b10100 4
b10100 ?
b10100 E
0O
b11011 ,
b101001 0
b11010 1
b11010 2
b11010 -
1'
1$
#460000
0'
#462000
0$
#465000
0V
b10110 5
b10110 f
b10110 j
b11011 (
b11011 3
b11011 ;
b11011 9
b11011 <
b11011 h
b11011 i
b11100 ,
b101010 0
b11011 1
b11011 2
1'
#469000
1J
b1011 7
b1011 @
b1011 D
b11001 A
b11001 F
b1100 !
b1100 8
b1100 >
b1101 :
b1101 =
b1101 B
b1101 C
1T
0W
b10101 4
b10101 ?
b10101 E
1X
1$
#470000
b11011 -
b1101 .
b1101 /
0'
#475000
0P
b10010 5
b10010 f
b10010 j
1"
b11100 (
b11100 3
b11100 ;
b11100 9
b11100 <
b11100 h
b11100 i
1K
b11101 ,
b101011 0
b11100 1
b11100 2
1'
#476000
0$
#480000
0'
#483000
0b
b11011 A
b11011 F
b1001 7
b1001 @
b1001 D
b1101 !
b1101 8
b1101 >
0X
b10110 4
b10110 ?
b10110 E
1U
0Q
b1110 :
b1110 =
b1110 B
b1110 C
1$
#484000
0%
b11100 -
b1110 .
b1110 /
#485000
0"
b1101 g
b1101 l
0)
b1011 6
b1011 e
b1011 k
1L
0c
b101100 0
1'
#490000
0'
0$
#495000
b1110 g
b1110 l
b11101 (
b11101 3
b11101 ;
1)
b1001 6
b1001 e
b1001 k
0d
b11110 ,
b101101 0
1'
#497000
b11100 A
b11100 F
b10010 4
b10010 ?
b10010 E
0R
b11101 -
1$
#500000
0'
#504000
0$
#505000
1V
b10011 5
b10011 f
b10011 j
b11110 (
b11110 3
b11110 ;
b11101 9
b11101 <
b11101 h
b11101 i
b11111 ,
b101110 0
b11101 1
b11101 2
1'
#510000
0'
#511000
1%
1W
b11110 -
1$
